model_filters/__init__.py
model_filters/apps.py
model_filters/constants.py
model_filters/utilities.py
model_filters/admin/__init__.py
model_filters/admin/field_filter_inline.py
model_filters/admin/list_filters.py
model_filters/admin/mixins.py
model_filters/admin/model_filter.py
model_filters/forms/__init__.py
model_filters/forms/field_filter.py
model_filters/forms/inline.py
model_filters/forms/model_filter.py
model_filters/forms/widgets.py
model_filters/managers/__init__.py
model_filters/managers/model_filter.py
model_filters/migrations/0001_initial.py
model_filters/migrations/__init__.py
model_filters/models/__init__.py
model_filters/models/field_filter.py
model_filters/models/model_filter.py
model_filters/static/model-filters/model-filters.css
model_filters/static/model-filters/model-filters.js
model_filters/templates/admin/model_filters/custom_change_form.html
model_filters/templates/admin/model_filters/custom_change_list.html
model_filters/templates/admin/model_filters/help.html
model_filters/templates/admin/model_filters/modelfilter/custom_change_list.html
model_filters/templates/admin/model_filters/modelfilter/submit_line.html
django_admin_model_filters-0.1.1.dist-info/LICENSE
django_admin_model_filters-0.1.1.dist-info/METADATA
django_admin_model_filters-0.1.1.dist-info/WHEEL
django_admin_model_filters-0.1.1.dist-info/top_level.txt
django_admin_model_filters-0.1.1.dist-info/RECORD
