Metadata-Version: 2.1
Name: django-admin-model-filters
Version: 0.1.1
Summary: A Django extension for filtering models by field value in the admin interface.
Home-page: https://github.com/barqshasbite/django-admin-model-filters
Author: Darren Maki
License: MIT
Keywords: django admin model field filter filters filtering
Platform: UNKNOWN
Classifier: Intended Audience :: Developers
Classifier: License :: OSI Approved :: MIT License
Classifier: Operating System :: OS Independent
Classifier: Framework :: Django
Classifier: Framework :: Django :: 2.2
Classifier: Framework :: Django :: 3.2
Classifier: Framework :: Django :: 4.0
Classifier: Programming Language :: Python
Classifier: Programming Language :: Python :: 3
Classifier: Programming Language :: Python :: 3.7
Classifier: Programming Language :: Python :: 3.9
Classifier: Programming Language :: Python :: Implementation :: CPython
License-File: LICENSE
